CMGDB/BoxMapData.py
CMGDB/ComputeBoxMap.py
CMGDB/LoadMorseSetFile.py
CMGDB/PlotMorseGraph.py
CMGDB/PlotMorseSets.py
CMGDB/SaveMorseData.py
CMGDB/_cmgdb.cp311-win_amd64.pyd
CMGDB/__init__.py
CMGDB/_cmgdb/CMGDB.cpp
CMGDB/_cmgdb/include/chomp/Algebra.h
CMGDB/_cmgdb/include/chomp/BitmapSubcomplex.h
CMGDB/_cmgdb/include/chomp/Chain.h
CMGDB/_cmgdb/include/chomp/Closure.h
CMGDB/_cmgdb/include/chomp/Complex.h
CMGDB/_cmgdb/include/chomp/ConleyIndex.h
CMGDB/_cmgdb/include/chomp/CoreductionDecomposer.h
CMGDB/_cmgdb/include/chomp/CubicalComplex.h
CMGDB/_cmgdb/include/chomp/Decomposer.h
CMGDB/_cmgdb/include/chomp/FiberComplex.h
CMGDB/_cmgdb/include/chomp/Field.h
CMGDB/_cmgdb/include/chomp/FrobeniusNormalForm.h
CMGDB/_cmgdb/include/chomp/Generators.h
CMGDB/_cmgdb/include/chomp/LICENSE
CMGDB/_cmgdb/include/chomp/Matrix.h
CMGDB/_cmgdb/include/chomp/MorseComplex.h
CMGDB/_cmgdb/include/chomp/PolyRing.h
CMGDB/_cmgdb/include/chomp/Preboundary.h
CMGDB/_cmgdb/include/chomp/Prism.h
CMGDB/_cmgdb/include/chomp/Real.h
CMGDB/_cmgdb/include/chomp/Rect.h
CMGDB/_cmgdb/include/chomp/RelativeMapHomology.h
CMGDB/_cmgdb/include/chomp/RelativePair.h
CMGDB/_cmgdb/include/chomp/Ring.h
CMGDB/_cmgdb/include/chomp/SmithNormalForm.h
CMGDB/_cmgdb/include/chomp/SparseMatrix.h
CMGDB/_cmgdb/include/database/Atlas.h
CMGDB/_cmgdb/include/database/AtlasGeo.h
CMGDB/_cmgdb/include/database/ChompMap.h
CMGDB/_cmgdb/include/database/CompressedTree.h
CMGDB/_cmgdb/include/database/CompressedTreeGrid.h
CMGDB/_cmgdb/include/database/Compute_Morse_Graph.h
CMGDB/_cmgdb/include/database/Compute_Morse_Graph.hpp
CMGDB/_cmgdb/include/database/Configuration.h
CMGDB/_cmgdb/include/database/conleyIndexString.h
CMGDB/_cmgdb/include/database/EdgeGrid.h
CMGDB/_cmgdb/include/database/EuclideanParameterSpace.h
CMGDB/_cmgdb/include/database/Geo.h
CMGDB/_cmgdb/include/database/GraphTheory.h
CMGDB/_cmgdb/include/database/GraphTheory.hpp
CMGDB/_cmgdb/include/database/Grid.h
CMGDB/_cmgdb/include/database/IntersectionGeo.h
cmgdb-1.3.1.dist-info/DELVEWHEEL
cmgdb-1.3.1.dist-info/METADATA
cmgdb-1.3.1.dist-info/RECORD
cmgdb-1.3.1.dist-info/WHEEL
cmgdb-1.3.1.dist-info/licenses/LICENSE
