Metadata-Version: 2.4
Name: CMGDB
Version: 1.3.1
Summary: CMGDB (Conley Morse Graph Database) Python Extension
Author-Email: Marcio Gameiro <marciogameiro@gmail.com>
License-Expression: MIT
License-File: LICENSE
Classifier: Development Status :: 5 - Production/Stable
Classifier: Intended Audience :: Science/Research
Classifier: Intended Audience :: Education
Classifier: Programming Language :: C++
Classifier: Programming Language :: Python
Classifier: Programming Language :: Python :: 3 :: Only
Classifier: Programming Language :: Python :: 3.9
Classifier: Programming Language :: Python :: 3.10
Classifier: Programming Language :: Python :: 3.11
Classifier: Programming Language :: Python :: 3.12
Classifier: Programming Language :: Python :: 3.13
Classifier: Operating System :: Microsoft :: Windows
Classifier: Operating System :: POSIX
Classifier: Operating System :: Unix
Classifier: Operating System :: MacOS
Project-URL: Repository, https://github.com/marciogameiro/CMGDB
Requires-Python: >=3.9
Requires-Dist: graphviz>=0.20
Requires-Dist: matplotlib>=3.6.0
Requires-Dist: numpy>=1.23.0
Provides-Extra: test
Requires-Dist: pytest; extra == "test"
